{
  "entity_checks": [],
  "fields": [
    {
      "protocols": {
        "default": ["grpc", "grpcs", "http", "https"],
        "description": "A set of strings representing HTTP protocols.",
        "elements": { "type": "string", "one_of": ["grpc", "grpcs", "http", "https"] },
        "required": true,
        "type": "set"
      }
    },
    {
      "config": {
        "fields": [
          {
            "http_method": {
              "type": "string",
              "match": "^%u+$",
              "description": "A string representing an HTTP method, such as GET, POST, PUT, or DELETE. The string must contain only uppercase letters."
            }
          },
          {
            "remove": {
              "fields": [
                { "body": { "elements": { "type": "string" }, "default": [], "type": "array" } },
                { "headers": { "elements": { "type": "string" }, "default": [], "type": "array" } },
                { "querystring": { "elements": { "type": "string" }, "default": [], "type": "array" } }
              ],
              "type": "record",
              "required": true
            }
          },
          {
            "rename": {
              "fields": [
                { "body": { "elements": { "type": "string", "referenceable": true }, "default": [], "type": "array" } },
                {
                  "headers": { "elements": { "type": "string", "referenceable": true }, "default": [], "type": "array" }
                },
                {
                  "querystring": {
                    "elements": { "type": "string", "referenceable": true },
                    "default": [],
                    "type": "array"
                  }
                }
              ],
              "type": "record",
              "required": true
            }
          },
          {
            "replace": {
              "fields": [
                { "body": { "elements": { "type": "string", "referenceable": true }, "default": [], "type": "array" } },
                {
                  "headers": { "elements": { "type": "string", "referenceable": true }, "default": [], "type": "array" }
                },
                {
                  "querystring": {
                    "elements": { "type": "string", "referenceable": true },
                    "default": [],
                    "type": "array"
                  }
                },
                {
                  "json_types": {
                    "elements": { "type": "string", "one_of": ["boolean", "number", "string"] },
                    "default": [],
                    "type": "array"
                  }
                },
                { "uri": { "type": "string" } }
              ],
              "type": "record",
              "required": true
            }
          },
          {
            "add": {
              "fields": [
                { "body": { "elements": { "type": "string", "referenceable": true }, "default": [], "type": "array" } },
                {
                  "headers": { "elements": { "type": "string", "referenceable": true }, "default": [], "type": "array" }
                },
                {
                  "querystring": {
                    "elements": { "type": "string", "referenceable": true },
                    "default": [],
                    "type": "array"
                  }
                },
                {
                  "json_types": {
                    "elements": { "type": "string", "one_of": ["boolean", "number", "string"] },
                    "default": [],
                    "type": "array"
                  }
                }
              ],
              "type": "record",
              "required": true
            }
          },
          {
            "append": {
              "fields": [
                { "body": { "elements": { "type": "string", "referenceable": true }, "default": [], "type": "array" } },
                {
                  "headers": { "elements": { "type": "string", "referenceable": true }, "default": [], "type": "array" }
                },
                {
                  "querystring": {
                    "elements": { "type": "string", "referenceable": true },
                    "default": [],
                    "type": "array"
                  }
                },
                {
                  "json_types": {
                    "elements": { "type": "string", "one_of": ["boolean", "number", "string"] },
                    "default": [],
                    "type": "array"
                  }
                }
              ],
              "type": "record",
              "required": true
            }
          },
          {
            "allow": {
              "fields": [{ "body": { "type": "set", "elements": { "type": "string" } } }],
              "type": "record",
              "required": true
            }
          },
          {
            "dots_in_keys": {
              "default": true,
              "type": "boolean",
              "description": "Specify whether dots (for example, `customers.info.phone`) should be treated as part of a property name or used to descend into nested JSON objects.  See [Arrays and nested objects](#arrays-and-nested-objects)."
            }
          }
        ],
        "type": "record",
        "required": true
      }
    }
  ]
}
